setup.cfg
setup.py
taz/__init__.py
taz.egg-info/PKG-INFO
taz.egg-info/SOURCES.txt
taz.egg-info/dependency_links.txt
taz.egg-info/entry_points.txt
taz.egg-info/not-zip-safe
taz.egg-info/requires.txt
taz.egg-info/top_level.txt
taz/commands/__init__.py
taz/commands/cli.py