Metadata-Version: 1.1
Name: taz
Version: 0.1.0
Summary: Taz Framework
Home-page: https://github.com/tazproject/taz
Author: Bruno Rocha
Author-email: rochacbruno@gmail.com
License: BSD
Platform: any
Classifier: Development Status :: 1 - Planning
Classifier: Environment :: Console
Classifier: Intended Audience :: Developers
Classifier: License :: OSI Approved :: BSD License
Classifier: Operating System :: POSIX
Classifier: Operating System :: MacOS
Classifier: Operating System :: Unix
Classifier: Programming Language :: Python
Classifier: Programming Language :: Python :: 2
Classifier: Programming Language :: Python :: 3
Classifier: Topic :: Software Development :: Libraries :: Python Modules
